{
	"ua": "Mozilla/5.0 (iPhone; CPU iPhone OS 13_2_3 like Mac OS X) AppleWebKit/605.1.15 (KHTML, like Gecko) Version/13.0.3 Mobile/15E148 Safari/604.1",
	"homeUrl": "https://www.xawqxh.net",	
	"cateManual": {
                "Netflix(片)": "1---Netflix-----",
                "Netflix(剧)": "2---Netflix-----",
                "Netflix(漫)": "4---Netflix-----",
                "热播电影": "1--hits------",
                "热播连续剧": "13--------",
		"电影": "1--------",
		"连续剧": "2--------",
                "福利": "124--------",
		"综艺纪录": "3--------",
		"动漫": "4--------"
		
	},
	"cateUrl": "https://www.xawqxh.net/vodshow/{cateId}{catePg}---.html",
	"cateVodNode": "//div[contains(@class, 'module-items module-poster-items-base')]//a",
	"cateVodName": "/div[contains(@class, 'module-poster-item-info')]/div/text()",
	"cateVodId": "/@href",
	"cateVodIdR": "/voddetail/(\\S+).html",
	"cateVodImg": "/div[contains(@class, 'module-item-cover')]/div[3]/img/@data-original",
	"cateVodImgR": "\\S+(http\\S+)",
	"cateVodMark": "/div[contains(@class, 'module-item-cover')]/div[2]/text()",
	"dtUrl": "https://www.xawqxh.net/voddetail/{vid}.html",
	"dtNode": "//div[contains(@class,'module-main')]",
	"dtName": "/div[@class='module-info-main']/div[contains(@class,'module-info-heading')]/h1/text()",
	"dtNameR": "",
	"dtImg": "/div[@class='module-info-poster']/div/div/img/@data-original",
	"dtImgR": "\\S+(http\\S+)",
	"dtCate": "//div[contains(@class,'module-info-tag')]/div[3]/a/text()",
	"dtCateR": "",
	"dtYear": "//div[contains(@class,'module-info-tag')]/div[1]/a/text()",
	"dtYearR": "",
	"dtArea": "//div[contains(@class,'module-info-tag')]/div[2]/a/text()",
	"dtAreaR": "",
	"dtMark": "//span[contains(text(), '备注')]/parent::*/div/text()",
	"dtMarkR": "",
	"dtActor": "//span[contains(text(), '主演')]/parent::*/div//a/text()",
	"dtActorR": "",
	"dtDirector": "//span[contains(text(), '导演')]/parent::*/div/a/text()",
	"dtDirectorR": "",
	"dtDesc": "//div[@class='module-info-introduction-content show-desc']//p/text()",
	"dtDescR": "",
	"dtFromNode": "//div[@class='module-tab-item tab-item']/span",
	"dtFromName": "/text()",
	"dtFromNameR": "",
	"dtUrlNode": "//div[contains(@id,'panel1')]/div/div",
	"dtUrlSubNode": "/a",
	"dtUrlId": "@href",
	"dtUrlIdR": "/vodplay/(\\S+).html",
	"dtUrlName": "/span/text()",
	"dtUrlNameR": "",
	"playUrl": "https://www.xawqxh.net/vodplay/{playUrl}.html",
	"playUa": "",
	"searchUrl": "https://www.xawqxh.net/index.php/ajax/suggest?mid=1&wd={wd}&limit=10",
	"scVodNode": "json:list",
	"scVodName": "name",
	"scVodId": "id",
	"scVodIdR": "",
	"scVodImg": "pic",
	"scVodMark": ""
}
